{
    "key": "group_603802e340a9a",
    "title": "Image Gallery Section Configuration",
    "fields": [
        {
            "key": "field_60638340b89da",
            "label": "Images",
            "name": "",
            "type": "accordion",
            "instructions": "",
            "required": 0,
            "conditional_logic": 0,
            "wrapper": {
                "width": "",
                "class": "",
                "id": ""
            },
            "open": 0,
            "multi_expand": 0,
            "endpoint": 0
        },
        {
            "key": "field_603802f891dc5",
            "label": "Images",
            "name": "images",
            "type": "gallery",
            "instructions": "Must Add more than one image for this block to work.",
            "required": 0,
            "conditional_logic": 0,
            "wrapper": {
                "width": "",
                "class": "",
                "id": ""
            },
            "return_format": "array",
            "preview_size": "medium",
            "insert": "prepend",
            "library": "all",
            "min": "",
            "max": "",
            "min_width": "",
            "min_height": "",
            "min_size": "",
            "max_width": "",
            "max_height": "",
            "max_size": "",
            "mime_types": ""
        },
        {
            "key": "field_6063835bb89db",
            "label": "Images Accordion Endpoint",
            "name": "",
            "type": "accordion",
            "instructions": "",
            "required": 0,
            "conditional_logic": 0,
            "wrapper": {
                "width": "",
                "class": "",
                "id": ""
            },
            "open": 0,
            "multi_expand": 0,
            "endpoint": 1
        },
        {
            "key": "field_6063836bb89dc",
            "label": "Image Gallery Configuration",
            "name": "",
            "type": "accordion",
            "instructions": "",
            "required": 0,
            "conditional_logic": 0,
            "wrapper": {
                "width": "",
                "class": "",
                "id": ""
            },
            "open": 0,
            "multi_expand": 0,
            "endpoint": 0
        },
        {
            "key": "field_606383a0b89de",
            "label": "Autoplay",
            "name": "autoplay",
            "type": "true_false",
            "instructions": "",
            "required": 0,
            "conditional_logic": 0,
            "wrapper": {
                "width": "",
                "class": "",
                "id": ""
            },
            "message": "Enable Auto Play?",
            "default_value": 1,
            "ui": 1,
            "ui_on_text": "",
            "ui_off_text": ""
        },
        {
            "key": "field_606383fbb89df",
            "label": "Autoplay Speed",
            "name": "autoplay_speed",
            "type": "number",
            "instructions": "How long before Autoplay goes to next slide.\r\nNote: 1000ms = 1s.",
            "required": 0,
            "conditional_logic": 0,
            "wrapper": {
                "width": "",
                "class": "",
                "id": ""
            },
            "default_value": 5000,
            "placeholder": "",
            "prepend": "",
            "append": "ms",
            "min": 1000,
            "max": "",
            "step": ""
        },
        {
            "key": "field_60638380b89dd",
            "label": "Image Gallery Configuration Accordion Endpoint",
            "name": "",
            "type": "accordion",
            "instructions": "",
            "required": 0,
            "conditional_logic": 0,
            "wrapper": {
                "width": "",
                "class": "",
                "id": ""
            },
            "open": 0,
            "multi_expand": 0,
            "endpoint": 1
        }
    ],
    "location": [
        [
            {
                "param": "block",
                "operator": "==",
                "value": "acf\/xten-section-image-gallery"
            }
        ]
    ],
    "menu_order": 0,
    "position": "side",
    "style": "default",
    "label_placement": "top",
    "instruction_placement": "label",
    "hide_on_screen": "",
    "active": 1,
    "description": "",
    "modified": 1617135346
}